tidycal/__init__.py
tidycal/client.py
tidycal/exceptions.py
tidycal_python-0.1.4.dist-info/LICENSE
tidycal_python-0.1.4.dist-info/METADATA
tidycal_python-0.1.4.dist-info/WHEEL
tidycal_python-0.1.4.dist-info/RECORD
